README.rst
setup.cfg
setup.py
simple_benchmark/__init__.py
simple_benchmark/__main__.py
simple_benchmark.egg-info/PKG-INFO
simple_benchmark.egg-info/SOURCES.txt
simple_benchmark.egg-info/dependency_links.txt
simple_benchmark.egg-info/not-zip-safe
simple_benchmark.egg-info/requires.txt
simple_benchmark.egg-info/top_level.txt