Metadata-Version: 2.1
Name: simple-benchmark
Version: 0.1.0
Summary: A simple benchmarking package.
Home-page: https://github.com/MSeifert04/simple_benchmark
Author: Michael Seifert
Author-email: michaelseifert04@yahoo.de
License: Apache License Version 2.0
Keywords: performance timing timeit
Platform: Windows Linux Mac OS-X
Classifier: Development Status :: 3 - Alpha
Classifier: Programming Language :: Python :: 2
Classifier: Programming Language :: Python :: 2.7
Classifier: Programming Language :: Python :: 3
Classifier: Programming Language :: Python :: 3.3
Classifier: Programming Language :: Python :: 3.4
Classifier: Programming Language :: Python :: 3.5
Classifier: Programming Language :: Python :: 3.6
Classifier: Operating System :: MacOS :: MacOS X
Classifier: Operating System :: Microsoft :: Windows
Classifier: Operating System :: POSIX :: Linux
Classifier: Topic :: Utilities
Classifier: Topic :: System :: Benchmark
Provides-Extra: optional
Provides-Extra: development
Provides-Extra: maintainer
